hybig/__init__.py
hybig/browse.py
hybig/browse_utility.py
hybig/color_utility.py
hybig/crs.py
hybig/exceptions.py
hybig/sizes.py
hybig_py-2.6.1.dist-info/METADATA
hybig_py-2.6.1.dist-info/WHEEL
hybig_py-2.6.1.dist-info/licenses/LICENSE
hybig_py-2.6.1.dist-info/RECORD
