Metadata-Version: 2.4
Name: hybig-py
Version: 2.6.1
Summary: Python package designed to produce browse imagery compatible with NASA's Global Image Browse Services (GIBS).
Project-URL: Homepage, https://github.com/nasa/harmony-browse-image-generator
Project-URL: Issues, https://github.com/nasa/harmony-browse-image-generator/issues
Author-email: Matt Savoie <savoie@colorado.edu>, Owen Littlejohns <owen.m.littlejohns@nasa.gov>, Jacqueline Ryan <Jacqueline.Ryan@jpl.nasa.gov>, Mauricio Hess-Flores <Mauricio.A.Hess.Flores@jpl.nasa.gov>
Maintainer-email: Jacqueline Ryan <Jacqueline.Ryan@jpl.nasa.gov>, Mauricio Hess-Flores <Mauricio.A.Hess.Flores@jpl.nasa.gov>
License-File: LICENSE
Classifier: License :: OSI Approved :: Apache Software License
Classifier: Operating System :: OS Independent
Classifier: Programming Language :: Python :: 3
Requires-Python: >=3.10
Requires-Dist: gdal==3.12.1
Requires-Dist: harmony-service-lib~=2.11.0
Requires-Dist: matplotlib==3.9.0
Requires-Dist: numpy==1.26.4
Requires-Dist: pillow==10.4.0
Requires-Dist: pyproj==3.6.1
Requires-Dist: pystac~=1.0.1
Requires-Dist: rasterio==1.3.10
